utbone/__init__.py
utbone/utbone.py
utbone/bones/__init__.py
utbone/bones/django-toppings.py
utbone/bones/django.py
utbone/bones/unit-toppings.py
utbone/bones/unit.py
utbone/tests/__init__.py
utbone-0.1.0.dist-info/DESCRIPTION.rst
utbone-0.1.0.dist-info/METADATA
utbone-0.1.0.dist-info/RECORD
utbone-0.1.0.dist-info/WHEEL
utbone-0.1.0.dist-info/entry_points.txt
utbone-0.1.0.dist-info/metadata.json
utbone-0.1.0.dist-info/top_level.txt
